ionq/__init__.py
ionq/ansatz/__init__.py
ionq/ansatz/ansatz_library.py
ionq/circuit.py
ionq/client/__init__.py
ionq/client/client.py
ionq/client/resource.py
ionq/client/resources/__init__.py
ionq/client/resources/backends.py
ionq/client/resources/jobs.py
ionq/defaults.py
ionq/errors.py
ionq/jobs/__init__.py
ionq/jobs/backend.py
ionq/jobs/base.py
ionq/jobs/circuit.py
ionq/jobs/optimization.py
ionq/jobs/quantum_function.py
ionq/problems/__init__.py
ionq/problems/problem.py
ionq/problems/quadratic.py
ionq/schemas/__init__.py
ionq/schemas/backend.py
ionq/schemas/characterization.py
ionq/schemas/circuit.py
ionq/schemas/job.py
ionq/utils/__init__.py
ionq/utils/ionq_qiskit.py
ionq/utils/utils.py
ionq-0.0.0a7.dist-info/LICENSE
ionq-0.0.0a7.dist-info/METADATA
ionq-0.0.0a7.dist-info/WHEEL
ionq-0.0.0a7.dist-info/entry_points.txt
ionq-0.0.0a7.dist-info/RECORD
