Metadata-Version: 2.1
Name: ionq
Version: 0.0.0a7
Summary: A Python library for interacting with IonQ's quantum computing API
Author: Spencer Churchill
Author-email: churchill@ionq.co
Requires-Python: >=3.9,<3.13
Classifier: Programming Language :: Python :: 3
Classifier: Programming Language :: Python :: 3.9
Classifier: Programming Language :: Python :: 3.10
Classifier: Programming Language :: Python :: 3.11
Classifier: Programming Language :: Python :: 3.12
Provides-Extra: all
Provides-Extra: hybrid
Requires-Dist: matplotlib (>=3,<4) ; extra == "hybrid" or extra == "all"
Requires-Dist: networkx (>=3,<4) ; extra == "hybrid" or extra == "all"
Requires-Dist: openqasm3[parser] (>=1,<2) ; extra == "hybrid" or extra == "all"
Requires-Dist: plotext (>=5,<6) ; extra == "hybrid" or extra == "all"
Requires-Dist: pydantic (>=1,<2)
Requires-Dist: pylatexenc (>=2,<3) ; extra == "hybrid" or extra == "all"
Requires-Dist: qiskit (>=1,<2) ; extra == "hybrid" or extra == "all"
Requires-Dist: requests (>=2,<3)
Requires-Dist: tqdm (>=4,<5) ; extra == "hybrid" or extra == "all"
